alvin_integration/__init__.py
alvin_integration/constants.py
alvin_integration/helper.py
alvin_integration/models.py
alvin_integration/installer/__init__.py
alvin_integration/installer/base.py
alvin_integration/interfaces/__init__.py
alvin_integration/interfaces/config.py
alvin_integration/producers/__init__.py
alvin_integration/producers/airflow/__init__.py
alvin_integration/producers/airflow/config.py
alvin_integration/producers/airflow/installer.py
alvin_integration/producers/airflow/lineage/__init__.py
alvin_integration/producers/airflow/lineage/alvin_plugin.py
alvin_integration/producers/airflow/lineage/backend.py
alvin_integration/producers/airflow/lineage/extractors/__init__.py
alvin_integration/producers/airflow/lineage/extractors/bigquery.py
alvin_integration/producers/airflow/lineage/extractors/mixins.py
alvin_integration/producers/airflow/lineage/extractors/snowflake.py
alvin_integration/producers/airflow/patch/__init__.py
alvin_integration/producers/airflow/patch/functions.py
alvin_integration/producers/airflow/patch/functions_legacy.py
alvin_integration/producers/airflow/pipeline/__init__.py
alvin_integration/producers/airflow/pipeline/dag_metadata_current.py
alvin_integration/producers/airflow/pipeline/dag_metadata_legacy.py
alvin_integration/producers/airflow/pipeline/extractor.py
alvin_integration_beta-0.0.21.dist-info/LICENSE
alvin_integration_beta-0.0.21.dist-info/METADATA
alvin_integration_beta-0.0.21.dist-info/WHEEL
alvin_integration_beta-0.0.21.dist-info/top_level.txt
alvin_integration_beta-0.0.21.dist-info/RECORD
