Metadata-Version: 2.1
Name: alvin-integration-beta
Version: 0.0.21
Summary: Alvin lineage python library for integrations
Home-page: UNKNOWN
Author: Alvin
Author-email: tech@alvin.ai
License: UNKNOWN
Platform: UNKNOWN
Requires-Python: >=3.7
License-File: LICENSE
Requires-Dist: gorilla (==0.4.0)
Requires-Dist: openlineage-airflow (==0.6.1)
